folder_manager_api/__init__.py
folder_manager_api/__main__.py
folder_manager_api/folder_manager_api.py
folder_manager_api-1.0.1.dist-info/METADATA
folder_manager_api-1.0.1.dist-info/WHEEL
folder_manager_api-1.0.1.dist-info/entry_points.txt
folder_manager_api-1.0.1.dist-info/top_level.txt
folder_manager_api-1.0.1.dist-info/RECORD
