Metadata-Version: 2.1
Name: folder_manager_api
Version: 1.0.1
Summary: A FastAPI wrapper for the folder_manager package, providing a RESTful API for managing folders and files.
Home-page: https://github.com/phintegrator/folder_manager_api
Author: Javer Valino
Classifier: Programming Language :: Python :: 3
Classifier: License :: OSI Approved :: MIT License
Classifier: Operating System :: OS Independent
Requires-Python: >=3.6
Requires-Dist: fastapi
Requires-Dist: fastapi-cors
Requires-Dist: uvicorn
Requires-Dist: pydantic
Requires-Dist: folder-manager
